ebotsphs25/__init__.py
ebotsphs25/bfs.py
ebotsphs25/connect4.py
ebotsphs25/maze.py
ebotsphs25/pattern.py
ebotsphs25/tictactoe.py
sphsebot25-0.1.0.dist-info/METADATA
sphsebot25-0.1.0.dist-info/WHEEL
sphsebot25-0.1.0.dist-info/top_level.txt
sphsebot25-0.1.0.dist-info/RECORD
