Metadata-Version: 2.4
Name: sphsebot25
Version: 0.1.0
Summary: A smart AI-based games and logic package including maze solving, Connect4, TicTacToe, and pattern prediction.
Author: Your Name
Author-email: your.email@example.com
Classifier: Programming Language :: Python :: 3
Classifier: License :: OSI Approved :: MIT License
Classifier: Operating System :: OS Independent
Requires-Python: >=3.6
Requires-Dist: numpy
Requires-Dist: matplotlib
Requires-Dist: seaborn
Requires-Dist: python-chess
Requires-Dist: chess
Dynamic: author
Dynamic: author-email
Dynamic: classifier
Dynamic: requires-dist
Dynamic: requires-python
Dynamic: summary
